README.txt
setup.py
email_hunter/__init__.py
email_hunter/cli.py
email_hunter/email_hunter_client.py
email_hunter_python.egg-info/PKG-INFO
email_hunter_python.egg-info/SOURCES.txt
email_hunter_python.egg-info/dependency_links.txt
email_hunter_python.egg-info/entry_points.txt
email_hunter_python.egg-info/requires.txt
email_hunter_python.egg-info/top_level.txt
test/test_cli.py
test/test_email_hunter_client.py