Metadata-Version: 1.1
Name: email-hunter-python
Version: 1.0.1
Summary: Client for Email Hunter REST API
Home-page: https://github.com/tipsqueal/email-hunter-python
Author: Alan Vezina
Author-email: alan.vezina@gmail.com
License: MIT
Keywords: email hunter client rest api cli
Platform: UNKNOWN
Classifier: Development Status :: 5 - Production/Stable
Classifier: Natural Language :: English
Classifier: License :: OSI Approved :: MIT License
Classifier: Programming Language :: Python
Classifier: Programming Language :: Python :: 3
Classifier: Programming Language :: Python :: 3.3
Classifier: Programming Language :: Python :: 3.4
Classifier: Programming Language :: Python :: 3.5
Classifier: Topic :: Utilities
